rabbitmq_communicator/__init__.py
rabbitmq_communicator/communicator.py
rabbitmq_communicator/decorators.py
rabbitmq_communicator/message_processor.py
rabbitmq_communicator-0.1.0.dist-info/LICENSE
rabbitmq_communicator-0.1.0.dist-info/METADATA
rabbitmq_communicator-0.1.0.dist-info/WHEEL
rabbitmq_communicator-0.1.0.dist-info/RECORD
