Metadata-Version: 2.3
Name: rabbitmq-communicator
Version: 0.1.0
Summary: Python package for duplex rabbitmq communicator service
License: MIT License
Author: oskar
Author-email: oskar.mozdzen@gmail.com
Requires-Python: >=3.9,<4.0
Classifier: License :: Other/Proprietary License
Classifier: Programming Language :: Python :: 3
Classifier: Programming Language :: Python :: 3.9
Classifier: Programming Language :: Python :: 3.10
Classifier: Programming Language :: Python :: 3.11
Classifier: Programming Language :: Python :: 3.12
Classifier: Programming Language :: Python :: 3.13
Requires-Dist: aio-pika (>=9.5.5,<10.0.0)
